telegram_video_downloader/__init__.py
telegram_video_downloader/app.py
telegram_video_downloader-1.2.dist-info/LICENSE
telegram_video_downloader-1.2.dist-info/METADATA
telegram_video_downloader-1.2.dist-info/WHEEL
telegram_video_downloader-1.2.dist-info/entry_points.txt
telegram_video_downloader-1.2.dist-info/top_level.txt
telegram_video_downloader-1.2.dist-info/RECORD
