Metadata-Version: 2.2
Name: telegram-video-downloader
Version: 1.2
Summary: Command to download or serve HTTP video published on Telegram
Author: David Grau Martínez
Author-email: fe80grau@gmail.com
Keywords: telegram video download
License-File: LICENSE
Requires-Dist: quart
Requires-Dist: telethon
Requires-Dist: cryptg
Dynamic: author
Dynamic: author-email
Dynamic: keywords
Dynamic: requires-dist
Dynamic: summary
